revisit/StudyConfigSchema.json
revisit/__init__.py
revisit/models.py
revisit/revisit.py
revisit/widget.py
revisit/static/widget.css
revisit/static/widget.js
revisit-0.0.31.dist-info/METADATA
revisit-0.0.31.dist-info/WHEEL
revisit-0.0.31.dist-info/RECORD
