Metadata-Version: 2.4
Name: revisit
Version: 0.0.31
Requires-Dist: anywidget
Requires-Dist: pandas
Requires-Dist: pydantic>=2.10.5
Provides-Extra: dev
Requires-Dist: jupyterlab; extra == 'dev'
Requires-Dist: watchfiles; extra == 'dev'
